{
  "paper_id": "doi_10.3390_app13053353",
  "collection": "aluminosilicate",
  "title": "Bond Characterization in Cementitious Material Binders Using Fourier-Transform Infrared Spectroscopy",
  "authors": [
    {
      "name": "Moruf Olalekan Yusuf",
      "given_name": "",
      "family_name": "",
      "full_name": "",
      "orcid": "https://orcid.org/0000-0002-8134-5435",
      "affiliation": "University of Hafr Al-Batin"
    }
  ],
  "doi": "10.3390/app13053353",
  "url": "https://doi.org/10.3390/app13053353",
  "published": "2023-03-06",
  "abstract": "Fourier-transform infrared (FTIR) spectroscopy is a fast and simple technique for functional group identification. This work provides a review and insight into the application and interpretation of FTIR spectroscopy for cementitious binders that comprise ordinary Portland cement, alkaline-activated binders, geopolymers, and material characterization for civil engineering material applications. This technique can be used to identify different compounds and a moiety of bond vibrations in inorganic molecules such as Si-O, -OH, H-O-H (water), C-O (carbonate or carbonation), aluminosilicate (Si-O-T, where T is Al or Si), and S-O (sulfate or gypsum) found in hydrated cement, alkaline binders, and geopolymers. The prominent bands include those representing carbonation (CO32− 1390–1475 cm−1), calcium carbonate (871, 1792–2516 cm−1), hydroxylation and water molecules (1607, 3400–3650 cm−1), strength skeletal framework compositions or Al-Si substitutions, silicate organization (C-A-S-H, N-A-S-H, or C-S-H (950–1055 cm−1), and sulfate (600–680, 1080–1100 cm−1). Some of the factors that could affect the spectra bands include elemental displacement due to changes in molar mass, activated temperature, pH, activator concentration, w/b ratio, Ca/Si ratio, Si/Al ratio, and the silica modulus (SiO2/Na2O) of the activators used in the binder synthesis. The method could be used for destructive and non-destructive testing on paste sample by using transmission and attenuated total reflectance methods, respectively.",
  "keywords": [
    "Fourier transform infrared spectroscopy",
    "Materials science",
    "Carbonation",
    "Infrared spectroscopy",
    "Cementitious",
    "Mineralogy",
    "Chemical engineering",
    "Cement",
    "Composite material",
    "Chemistry"
  ],
  "source": "openalex",
  "source_id": "W4323365469",
  "pdf_path": "aluminosilicate\\papers\\doi_10.3390_app13053353\\paper.pdf",
  "pdf_url": "https://www.mdpi.com/2076-3417/13/5/3353/pdf?version=1678104164",
  "pdf_accessible": false,
  "links": [],
  "license_info": "",
  "is_open_access": false,
  "oa_status": "",
  "citation_count": 280,
  "journal": "Applied Sciences",
  "publisher": "",
  "issn": "2076-3417",
  "quartile": "",
  "added_at": "2026-05-22T05:33:40.960446+00:00",
  "updated_at": "",
  "extra": {
    "journal_cites_per_year": 0.0
  }
}